{"Code": "EXEC SQL UPDATE seguros.v0bilhete SET COD_AGENCIA_DEB = :COD_AGENCIA_DEB, OPERACAO_CONTA_DEB = :OPERACAO_CONTA_DEB, NUM_CONTA_DEB = :NUM_CONTA_DEB, DIG_CONTA_DEB = :DIG_CONTA_DEB WHERE NUMBIL = :NUMBIL END SQL", "Inputs": [{"Field": ":COD_AGENCIA_DEB", "Type": "string"}, {"Field": ":OPERACAO_CONTA_DEB", "Type": "string"}, {"Field": ":NUM_CONTA_DEB", "Type": "string"}, {"Field": ":DIG_CONTA_DEB", "Type": "string"}, {"Field": ":NUMBIL", "Type": "string"}], "Outputs": [], "Endpoint": "bi14a/bi14p012"}