{"Code": "EXEC SQL  SELECT T1.NUM_APOLICE, T1.NRENDOST1.NRPARCEL\nFROM seguros.v1parcela\n \nWHERE\n       t1.num_apolice   =     :NUM_APOLICE\n  and  t1.nrendos       =     :NRENDOS\n  and  t1.num_apolice   =     t2.num_apolice\n  and  t1.nrendos       =     t2.nrendos\n  and  t1.nrparcel      =     t2.nrparcel\n  and  t2.ocorhist      =     1\n:esql.\n:sql       clause    = ORDERBY      hostvar = ':'.\norder by 1, 2, 3\n/\nORDER BY END SQL", "Inputs": [{"Field": ":NUM_APOLICE", "Type": "string"}, {"Field": ":NRENDOS", "Type": "string"}], "Outputs": [{"Field": "T1", "Type": "string"}, {"Field": "NUM_APOLICE", "Type": "string"}, {"Field": "T1", "Type": "string"}, {"Field": "NRENDOS", "Type": "string"}, {"Field": "T1", "Type": "string"}, {"Field": "NRPARCEL", "Type": "string"}], "Endpoint": "ac74a/AC74P003"}