{"Code": "EXEC SQL  SELECT congener, char(dtmovto_aclocal)char(dtliberalocal)\nFROM seguros.v0cosced_cheque\n \nwhere congener = :CONGENER\nand (dtmovto_fi is null\n or  dtmovto_fi = :DTMOVABE)\nand situacao in (' ','0','1')\n/\n END SQL", "Inputs": [{"Field": ":CONGENER", "Type": "string"}, {"Field": ":DTMOVABE", "Type": "string"}], "Outputs": [{"Field": "congener", "Type": "string"}, {"Field": "char", "Type": "string"}, {"Field": "dtmovto_ac", "Type": "string"}, {"Field": "local", "Type": "string"}, {"Field": "char", "Type": "string"}, {"Field": "dtlibera", "Type": "string"}, {"Field": "local", "Type": "string"}], "Endpoint": "ac08a/AC08P35"}