{
  "QueryDescription": {
    "Inserts": 0,
    "Updates": 0,
    "Deletes": 0,
    "Selects": 6,
    "Cursors": 2,
    "Procedures": 0,
    "All": 8
  },
  "MethodDescription": {
    "ProgramName": "SI0220B",
    "Quantity": 34,
    "Methods": [
      {
        "EntraceMethod": true,
        "Lines": 30,
        "Name": "Execute",
        "IgnoredMethod": false,
        "Parameters": [
          "string REG_RET_FILE_NAME_P"
        ],
        "Obs": "",
        "Calls": [
          "R010_LE_SISTEMAS",
          "R010_EXIT",
          "R015_LE_MONTA_NOME_EMPRESA",
          "R015_EXIT",
          "R020_LE_PROVISAO_DIA",
          "R020_EXIT",
          "R021_FETCH_PROVISAO",
          "R021_EXIT",
          "R100_PROCESSA_PROVISAO",
          "R100_EXIT"
        ]
      },
      {
        "EntraceMethod": false,
        "Lines": 17,
        "Name": "R010_LE_SISTEMAS",
        "IgnoredMethod": false,
        "Parameters": [],
        "Obs": "",
        "Calls": [
          "R9999_00_ROT_ERRO"
        ]
      },
      {
        "EntraceMethod": false,
        "Lines": 1,
        "Name": "R010_LE_SISTEMAS_DB_SELECT_1",
        "IgnoredMethod": false,
        "Parameters": [],
        "Obs": "",
        "Calls": []
      },
      {
        "EntraceMethod": false,
        "Lines": 1,
        "Name": "R010_EXIT",
        "IgnoredMethod": true,
        "Parameters": [],
        "Obs": "Método ignorado por falta de comandos",
        "Calls": []
      },
      {
        "EntraceMethod": false,
        "Lines": 9,
        "Name": "R015_LE_MONTA_NOME_EMPRESA",
        "IgnoredMethod": false,
        "Parameters": [],
        "Obs": "",
        "Calls": []
      },
      {
        "EntraceMethod": false,
        "Lines": 1,
        "Name": "R015_LE_MONTA_NOME_EMPRESA_DB_SELECT_1",
        "IgnoredMethod": false,
        "Parameters": [],
        "Obs": "",
        "Calls": []
      },
      {
        "EntraceMethod": false,
        "Lines": 1,
        "Name": "R015_EXIT",
        "IgnoredMethod": true,
        "Parameters": [],
        "Obs": "Método ignorado por falta de comandos",
        "Calls": []
      },
      {
        "EntraceMethod": false,
        "Lines": 5,
        "Name": "R020_LE_PROVISAO_DIA",
        "IgnoredMethod": false,
        "Parameters": [],
        "Obs": "",
        "Calls": [
          "R10010199_MENSAGEM_LOCK"
        ]
      },
      {
        "EntraceMethod": false,
        "Lines": 1,
        "Name": "R020_LE_PROVISAO_DIA_DB_DECLARE_1",
        "IgnoredMethod": false,
        "Parameters": [],
        "Obs": "",
        "Calls": []
      },
      {
        "EntraceMethod": false,
        "Lines": 1,
        "Name": "R020_LE_PROVISAO_DIA_DB_OPEN_1",
        "IgnoredMethod": false,
        "Parameters": [],
        "Obs": "",
        "Calls": []
      },
      {
        "EntraceMethod": false,
        "Lines": 1,
        "Name": "R110_LE_CONTRATO_CLIENTE_DB_DECLARE_1",
        "IgnoredMethod": false,
        "Parameters": [],
        "Obs": "",
        "Calls": []
      },
      {
        "EntraceMethod": false,
        "Lines": 1,
        "Name": "R020_EXIT",
        "IgnoredMethod": true,
        "Parameters": [],
        "Obs": "Método ignorado por falta de comandos",
        "Calls": []
      },
      {
        "EntraceMethod": false,
        "Lines": 10,
        "Name": "R021_FETCH_PROVISAO",
        "IgnoredMethod": false,
        "Parameters": [],
        "Obs": "",
        "Calls": [
          "R9999_00_ROT_ERRO"
        ]
      },
      {
        "EntraceMethod": false,
        "Lines": 1,
        "Name": "R021_FETCH_PROVISAO_DB_FETCH_1",
        "IgnoredMethod": false,
        "Parameters": [],
        "Obs": "",
        "Calls": []
      },
      {
        "EntraceMethod": false,
        "Lines": 1,
        "Name": "R021_EXIT",
        "IgnoredMethod": true,
        "Parameters": [],
        "Obs": "Método ignorado por falta de comandos",
        "Calls": []
      },
      {
        "EntraceMethod": false,
        "Lines": 48,
        "Name": "R100_PROCESSA_PROVISAO",
        "IgnoredMethod": false,
        "Parameters": [],
        "Obs": "",
        "Calls": [
          "R021_FETCH_PROVISAO",
          "R021_EXIT",
          "R110_LE_CONTRATO_CLIENTE",
          "R110_EXIT",
          "R130_LE_AGENCIA_CONTRATO",
          "R130_EXIT"
        ]
      },
      {
        "EntraceMethod": false,
        "Lines": 1,
        "Name": "R100_EXIT",
        "IgnoredMethod": true,
        "Parameters": [],
        "Obs": "Método ignorado por falta de comandos",
        "Calls": []
      },
      {
        "EntraceMethod": false,
        "Lines": 50,
        "Name": "R110_LE_CONTRATO_CLIENTE",
        "IgnoredMethod": false,
        "Parameters": [],
        "Obs": "",
        "Calls": [
          "R110_EXIT",
          "R120_BUSCA_CLIENTE",
          "R9999_00_ROT_ERRO"
        ]
      },
      {
        "EntraceMethod": false,
        "Lines": 1,
        "Name": "R110_LE_CONTRATO_CLIENTE_DB_SELECT_1",
        "IgnoredMethod": false,
        "Parameters": [],
        "Obs": "",
        "Calls": []
      },
      {
        "EntraceMethod": false,
        "Lines": 1,
        "Name": "R110_EXIT",
        "IgnoredMethod": true,
        "Parameters": [],
        "Obs": "Método ignorado por falta de comandos",
        "Calls": []
      },
      {
        "EntraceMethod": false,
        "Lines": 1,
        "Name": "R110_LE_CONTRATO_CLIENTE_DB_OPEN_1",
        "IgnoredMethod": false,
        "Parameters": [],
        "Obs": "",
        "Calls": []
      },
      {
        "EntraceMethod": false,
        "Lines": 1,
        "Name": "R110_LE_CONTRATO_CLIENTE_DB_FETCH_1",
        "IgnoredMethod": false,
        "Parameters": [],
        "Obs": "",
        "Calls": []
      },
      {
        "EntraceMethod": false,
        "Lines": 1,
        "Name": "R110_LE_CONTRATO_CLIENTE_DB_CLOSE_1",
        "IgnoredMethod": false,
        "Parameters": [],
        "Obs": "",
        "Calls": []
      },
      {
        "EntraceMethod": false,
        "Lines": 1,
        "Name": "R110_LE_CONTRATO_CLIENTE_DB_SELECT_2",
        "IgnoredMethod": false,
        "Parameters": [],
        "Obs": "",
        "Calls": []
      },
      {
        "EntraceMethod": false,
        "Lines": 8,
        "Name": "R120_BUSCA_CLIENTE",
        "IgnoredMethod": false,
        "Parameters": [],
        "Obs": "",
        "Calls": [
          "R9999_00_ROT_ERRO"
        ]
      },
      {
        "EntraceMethod": false,
        "Lines": 1,
        "Name": "R120_BUSCA_CLIENTE_DB_SELECT_1",
        "IgnoredMethod": false,
        "Parameters": [],
        "Obs": "",
        "Calls": []
      },
      {
        "EntraceMethod": false,
        "Lines": 1,
        "Name": "R120_EXIT",
        "IgnoredMethod": true,
        "Parameters": [],
        "Obs": "Método ignorado por falta de comandos",
        "Calls": []
      },
      {
        "EntraceMethod": false,
        "Lines": 6,
        "Name": "R130_LE_AGENCIA_CONTRATO",
        "IgnoredMethod": false,
        "Parameters": [],
        "Obs": "",
        "Calls": [
          "R9999_00_ROT_ERRO"
        ]
      },
      {
        "EntraceMethod": false,
        "Lines": 1,
        "Name": "R130_LE_AGENCIA_CONTRATO_DB_SELECT_1",
        "IgnoredMethod": false,
        "Parameters": [],
        "Obs": "",
        "Calls": []
      },
      {
        "EntraceMethod": false,
        "Lines": 1,
        "Name": "R130_EXIT",
        "IgnoredMethod": true,
        "Parameters": [],
        "Obs": "Método ignorado por falta de comandos",
        "Calls": []
      },
      {
        "EntraceMethod": false,
        "Lines": 19,
        "Name": "R9999_00_ROT_ERRO",
        "IgnoredMethod": false,
        "Parameters": [],
        "Obs": "",
        "Calls": []
      },
      {
        "EntraceMethod": false,
        "Lines": 1,
        "Name": "R9999_EXIT",
        "IgnoredMethod": true,
        "Parameters": [],
        "Obs": "Método ignorado por falta de comandos",
        "Calls": []
      },
      {
        "EntraceMethod": false,
        "Lines": 34,
        "Name": "R10010199_MENSAGEM_LOCK",
        "IgnoredMethod": false,
        "Parameters": [],
        "Obs": "",
        "Calls": [
          "R9999_00_ROT_ERRO"
        ]
      },
      {
        "EntraceMethod": false,
        "Lines": 0,
        "Name": "R10010199_EXIT",
        "IgnoredMethod": false,
        "Parameters": [],
        "Obs": "",
        "Calls": []
      }
    ]
  },
  "CopyDescription": {
    "Quantity": 0,
    "Names": []
  },
  "DclDescription": {
    "Quantity": 17,
    "Names": [
      "SISTEMAS",
      "AGENCCEF",
      "EMPRESAS",
      "PRODUTO",
      "CLIENTES",
      "APOLICRE",
      "SINCREIN",
      "SINIHAB1",
      "FORNECED",
      "SI111",
      "SI112",
      "CALENDAR",
      "PAROPESI",
      "SINISMES",
      "SINISHIS",
      "PROVISAO",
      "CREDITO"
    ]
  },
  "FilesDescription": {
    "Quantity": 1,
    "Names": [
      "REG_RET0"
    ]
  }
}