{
  "QueryDescription": {
    "Inserts": 0,
    "Updates": 0,
    "Deletes": 0,
    "Selects": 1,
    "Cursors": 2,
    "Procedures": 0,
    "All": 3
  },
  "MethodDescription": {
    "ProgramName": "GECPB101",
    "Quantity": 20,
    "Methods": [
      {
        "EntraceMethod": true,
        "Lines": 1,
        "Name": "Execute",
        "IgnoredMethod": false,
        "Parameters": [
          "string CPB101S1_FILE_NAME_P",
          "string CPB101S2_FILE_NAME_P"
        ],
        "Obs": "",
        "Calls": [
          "R0000_00_PRINCIPAL_SECTION"
        ]
      },
      {
        "EntraceMethod": false,
        "Lines": 30,
        "Name": "R0000_00_PRINCIPAL_SECTION",
        "IgnoredMethod": false,
        "Parameters": [],
        "Obs": "",
        "Calls": []
      },
      {
        "EntraceMethod": false,
        "Lines": 1,
        "Name": "R0000_00_PRINCIPAL_DB_SELECT_1",
        "IgnoredMethod": false,
        "Parameters": [],
        "Obs": "",
        "Calls": []
      },
      {
        "EntraceMethod": false,
        "Lines": 22,
        "Name": "R0000_90_FINALIZA",
        "IgnoredMethod": false,
        "Parameters": [],
        "Obs": "",
        "Calls": []
      },
      {
        "EntraceMethod": false,
        "Lines": 1,
        "Name": "R0000_99_SAIDA",
        "IgnoredMethod": true,
        "Parameters": [],
        "Obs": "Método ignorado por falta de comandos",
        "Calls": []
      },
      {
        "EntraceMethod": false,
        "Lines": 42,
        "Name": "R0010_00_TRATA_CURSOR01_SECTION",
        "IgnoredMethod": false,
        "Parameters": [],
        "Obs": "",
        "Calls": []
      },
      {
        "EntraceMethod": false,
        "Lines": 1,
        "Name": "R0010_00_TRATA_CURSOR01_DB_OPEN_1",
        "IgnoredMethod": false,
        "Parameters": [],
        "Obs": "",
        "Calls": []
      },
      {
        "EntraceMethod": false,
        "Lines": 1,
        "Name": "R0010_99_SAIDA",
        "IgnoredMethod": true,
        "Parameters": [],
        "Obs": "Método ignorado por falta de comandos",
        "Calls": []
      },
      {
        "EntraceMethod": false,
        "Lines": 14,
        "Name": "R0015_00_FETCH_C01_SECTION",
        "IgnoredMethod": false,
        "Parameters": [],
        "Obs": "",
        "Calls": [
          "R0015_99_SAIDA"
        ]
      },
      {
        "EntraceMethod": false,
        "Lines": 1,
        "Name": "R0015_00_FETCH_C01_DB_FETCH_1",
        "IgnoredMethod": false,
        "Parameters": [],
        "Obs": "",
        "Calls": []
      },
      {
        "EntraceMethod": false,
        "Lines": 1,
        "Name": "R0015_00_FETCH_C01_DB_CLOSE_1",
        "IgnoredMethod": false,
        "Parameters": [],
        "Obs": "",
        "Calls": []
      },
      {
        "EntraceMethod": false,
        "Lines": 1,
        "Name": "R0015_99_SAIDA",
        "IgnoredMethod": true,
        "Parameters": [],
        "Obs": "Método ignorado por falta de comandos",
        "Calls": []
      },
      {
        "EntraceMethod": false,
        "Lines": 32,
        "Name": "R0020_00_TRATA_CURSOR02_SECTION",
        "IgnoredMethod": false,
        "Parameters": [],
        "Obs": "",
        "Calls": []
      },
      {
        "EntraceMethod": false,
        "Lines": 1,
        "Name": "R0020_00_TRATA_CURSOR02_DB_OPEN_1",
        "IgnoredMethod": false,
        "Parameters": [],
        "Obs": "",
        "Calls": []
      },
      {
        "EntraceMethod": false,
        "Lines": 1,
        "Name": "R0020_99_SAIDA",
        "IgnoredMethod": true,
        "Parameters": [],
        "Obs": "Método ignorado por falta de comandos",
        "Calls": []
      },
      {
        "EntraceMethod": false,
        "Lines": 14,
        "Name": "R0025_00_FETCH_C02_SECTION",
        "IgnoredMethod": false,
        "Parameters": [],
        "Obs": "",
        "Calls": [
          "R0025_99_SAIDA"
        ]
      },
      {
        "EntraceMethod": false,
        "Lines": 1,
        "Name": "R0025_00_FETCH_C02_DB_FETCH_1",
        "IgnoredMethod": false,
        "Parameters": [],
        "Obs": "",
        "Calls": []
      },
      {
        "EntraceMethod": false,
        "Lines": 1,
        "Name": "R0025_00_FETCH_C02_DB_CLOSE_1",
        "IgnoredMethod": false,
        "Parameters": [],
        "Obs": "",
        "Calls": []
      },
      {
        "EntraceMethod": false,
        "Lines": 1,
        "Name": "R0025_99_SAIDA",
        "IgnoredMethod": true,
        "Parameters": [],
        "Obs": "Método ignorado por falta de comandos",
        "Calls": []
      },
      {
        "EntraceMethod": false,
        "Lines": 5,
        "Name": "R9999_00_ROT_ERRO_SECTION",
        "IgnoredMethod": false,
        "Parameters": [],
        "Obs": "",
        "Calls": []
      }
    ]
  },
  "CopyDescription": {
    "Quantity": 0,
    "Names": []
  },
  "DclDescription": {
    "Quantity": 14,
    "Names": [
      "GE501",
      "GE536",
      "GE537",
      "GE540",
      "GE541",
      "GE547",
      "GE551",
      "GE552",
      "GE554",
      "GE577",
      "GE576",
      "GE543",
      "C01",
      "C02"
    ]
  },
  "FilesDescription": {
    "Quantity": 2,
    "Names": [
      "CPB101S10",
      "CPB101S20"
    ]
  }
}