{"Code": "EXEC SQL  SELECT MAX(NUM_OCORR_SINIACO)\nFROM SEGUROS.SI_SINISTRO_ACOMP\n \nWHERE COD_FONTE = :COD_FONTE\nAND NUM_PROTOCOLO_SINI = :NUM_PROTOCOLO_SINI\nAND DAC_PROTOCOLO_SINI = :DAC_PROTOCOLO_SINI\n/\n END SQL", "Inputs": [{"Field": ":COD_FONTE", "Type": "string"}, {"Field": ":NUM_PROTOCOLO_SINI", "Type": "string"}, {"Field": ":DAC_PROTOCOLO_SINI", "Type": "string"}], "Outputs": [{"Field": "MAX", "Type": "string"}, {"Field": "NUM_OCORR_SINIACO", "Type": "string"}], "Endpoint": "sixka/SIXKP044"}