{"Code": "EXEC SQL SELECT SUM(VALUE(PRM_TARIFARIO,0)), SUM(VALUE(VAL_DESCONTO,0)), SUM(VALUE(VLPRMLIQ,0)), SUM(VALUE(VLADIFRA,0)), SUM(VALUE(VLCUSEMI,0)), SUM(VALUE(VLIOCC,0)), SUM(VALUE(VLPRMTOT,0)), SUM(VALUE(VLPREMIO,0)), DTVENCTO FROM seguros.v1histoparc WHERE num_apolice = :NUM_APOLICE and nrendos = :NRENDOS and nrparcel = :NRPARCEL and operacao = :OPERACAO GROUP BY DTVENCTO END SQL", "Inputs": [{"Field": ":NUM_APOLICE", "Type": "string"}, {"Field": ":NRENDOS", "Type": "string"}, {"Field": ":NRPARCEL", "Type": "string"}, {"Field": ":OPERACAO", "Type": "string"}], "Outputs": [{"Field": "PRM_TARIFARIO", "Type": "string"}, {"Field": "VAL_DESCONTO", "Type": "string"}, {"Field": "VLPRMLIQ", "Type": "string"}, {"Field": "VLADIFRA", "Type": "string"}, {"Field": "VLCUSEMI", "Type": "string"}, {"Field": "VLIOCC", "Type": "string"}, {"Field": "VLPRMTOT", "Type": "string"}, {"Field": "VLPREMIO", "Type": "string"}, {"Field": "DTVENCTO", "Type": "string"}], "Endpoint": "cb2ma/cb2mp035"}